featuretools_sql/__init__.py
featuretools_sql/connector.py
featuretools_sql/version.py
featuretools_sql/db_connectors/__init__.py
featuretools_sql/db_connectors/mysql_connector.py
featuretools_sql/db_connectors/postgres_connector.py
featuretools_sql/db_connectors/snowflake_connector.py
featuretools_sql/tests/__init__.py
featuretools_sql/tests/test_version.py
featuretools_sql/tests/integration_tests/__init__.py
featuretools_sql/tests/integration_tests/mysql/__init__.py
featuretools_sql/tests/integration_tests/mysql/test_mysql_query.py
featuretools_sql/tests/integration_tests/postgres/__init__.py
featuretools_sql/tests/integration_tests/postgres/test_postgres_query.py
featuretools_sql/tests/requirement_files/latest_requirements.txt
featuretools_sql-0.0.5.dist-info/LICENSE
featuretools_sql-0.0.5.dist-info/METADATA
featuretools_sql-0.0.5.dist-info/WHEEL
featuretools_sql-0.0.5.dist-info/entry_points.txt
featuretools_sql-0.0.5.dist-info/top_level.txt
featuretools_sql-0.0.5.dist-info/RECORD
