Metadata-Version: 2.1
Name: featuretools-sql
Version: 0.0.5
Summary: directly import and convert their relational data into a Featuretools
Author: Alteryx, Inc.
Maintainer: Alteryx, Inc.
License: BSD 3-clause
Project-URL: Documentation, https://featuretools.alteryx.com
Project-URL: Source Code, https://github.com/alteryx/featuretools_sql/
Project-URL: Changes, https://github.com/alteryx/featuretools/blob/main/source/release_notes.rst
Project-URL: Issue Tracker, https://github.com/alteryx/featuretools_sql/issues
Project-URL: Twitter, https://twitter.com/alteryxoss
Project-URL: Chat, https://join.slack.com/t/alteryx-oss/shared_invite/zt-182tyvuxv-NzIn6eiCEf8TBziuKp0bNA
Keywords: relational data,sql,feature engineering,data science,machine learning
Classifier: Intended Audience :: Science/Research
Classifier: Intended Audience :: Developers
Classifier: Topic :: Software Development
Classifier: Topic :: Scientific/Engineering
Classifier: Operating System :: Microsoft :: Windows
Classifier: Operating System :: POSIX
Classifier: Operating System :: Unix
Classifier: Operating System :: MacOS
Classifier: Programming Language :: Python
Classifier: Programming Language :: Python :: 3
Classifier: Programming Language :: Python :: 3.8
Classifier: Programming Language :: Python :: 3.9
Classifier: Programming Language :: Python :: 3.10
Requires-Python: <4,>=3.8
License-File: LICENSE
Requires-Dist: numpy (>=1.17.5)
Requires-Dist: pandas (>=1.3.0)
Requires-Dist: featuretools (>=1.5.0)
Requires-Dist: psycopg2 (>=2.9.3)
Requires-Dist: sqlalchemy (>=1.4.2)
Requires-Dist: PyMySQL (>=1.0.2)
Requires-Dist: snowflake-sqlalchemy[pandas] (>=1.4.2)
Provides-Extra: dev
Requires-Dist: flake8 (==5.0.4) ; extra == 'dev'
Requires-Dist: isort (==5.10.1) ; extra == 'dev'
Requires-Dist: black (==22.6.0) ; extra == 'dev'
Requires-Dist: pre-commit (==2.20.0) ; extra == 'dev'
Requires-Dist: featuretools-sql[test] ; extra == 'dev'
Provides-Extra: test
Requires-Dist: pytest (>=7.1.2) ; extra == 'test'
Requires-Dist: pytest-cov (>=3.0.0) ; extra == 'test'
